{"id":2946,"questionCode":"06060188","questionTemplateId":1,"noteDisplayTypeCode":"XNA","questionFrameDisplayTypeCode":"XNA","answerTextDisplayTypeCode":"ALWAYS","questionTextDisplayTypeCode":"XNA","questionText":"Motorov\u00E9 vozidlo mus\u00ED m\u00EDt za j\u00EDzdy:","explanationNote":null,"maxNoOfDisplays":-1,"maxPostDisplayTime":-1,"basketScopeId":9,"basketScopeOrder":0,"pointsCount":2,"validFrom":"2006-06-13T00:00:00","validTo":"2099-12-31T00:00:00","answersOrder":"0000","questionAnswers":[{"id":28681,"answerText":"Zav\u0159ena bo\u010Dn\u00ED okna.","mediaContent":null,"sortOrderNumber":1,"isCorrect":false},{"id":28682,"answerText":"V\u017Edy rozsv\u00EDcena v\u0161echna sv\u011Btla.","mediaContent":null,"sortOrderNumber":2,"isCorrect":false},{"id":28683,"answerText":"Rozsv\u00EDcena obrysov\u00E1 sv\u011Btla a potk\u00E1vac\u00ED sv\u011Btla nebo sv\u011Btla pro denn\u00ED sv\u00EDcen\u00ED, pokud je jimi vybaveno podle zvl\u00E1\u0161tn\u00EDho pr\u00E1vn\u00EDho p\u0159edpisu.","mediaContent":null,"sortOrderNumber":3,"isCorrect":true}],"mediaContent":null}