{"id":4328,"questionCode":"10060036","questionTemplateId":1,"noteDisplayTypeCode":"XNA","questionFrameDisplayTypeCode":"XNA","answerTextDisplayTypeCode":"ALWAYS","questionTextDisplayTypeCode":"XNA","questionText":"\u0022\u00DA\u010Dastn\u00EDk provozu na pozemn\u00EDch komunikac\u00EDch\u0022:","explanationNote":null,"maxNoOfDisplays":-1,"maxPostDisplayTime":-1,"basketScopeId":9,"basketScopeOrder":0,"pointsCount":2,"validFrom":"2010-08-01T00:00:00","validTo":"2099-12-31T00:00:00","answersOrder":"0000","questionAnswers":[{"id":3424568,"answerText":"je pouze \u0159idi\u010D motorov\u00FDch vozidel a chodec.","mediaContent":null,"sortOrderNumber":1,"isCorrect":false},{"id":3424569,"answerText":"je ka\u017Ed\u00FD, kdo se p\u0159\u00EDm\u00FDm zp\u016Fsobem \u00FA\u010Dastn\u00ED provozu na pozemn\u00EDch komunikac\u00EDch.","mediaContent":null,"sortOrderNumber":2,"isCorrect":true},{"id":3424570,"answerText":"je ka\u017Ed\u00FD, kdo se \u00FA\u010Dastn\u00ED provozu na pozemn\u00EDch komunikac\u00EDch s v\u00FDjimkou d\u011Bt\u00ED.","mediaContent":null,"sortOrderNumber":3,"isCorrect":false}],"mediaContent":null}