{"id": 5435, "questionCode": "22020032", "questionTemplateId": 2, "noteDisplayTypeCode": "XNA", "questionFrameDisplayTypeCode": "XNA", "answerTextDisplayTypeCode": "ALWAYS", "questionTextDisplayTypeCode": "XNA", "questionText": "Může řidič přes tuto vodorovnou dopravní značku odbočit vlevo k najetí do garáže u rodinného domu?", "explanationNote": null, "maxNoOfDisplays": -1, "maxPostDisplayTime": -1, "basketScopeId": 11, "basketScopeOrder": 0, "pointsCount": 1, "validFrom": "2022-02-13T00:00:00", "validTo": "2100-01-01T00:00:00", "answersOrder": "0000", "questionAnswers": [{"id": 3429493, "answerText": "ANO", "mediaContent": null, "sortOrderNumber": 1, "isCorrect": true}, {"id": 3429494, "answerText": "NE", "mediaContent": null, "sortOrderNumber": 2, "isCorrect": false}], "mediaContent": {"printMediaName": "Q_W_5435.png", "mediaUrl": "/binary_content_storage/Q_W_5435.png", "mediaDataHash": "00cd55a8d017a9c3efa41f2802bc46f63bf76d306ab04c3826e190e73ae7d1ee", "mediaFormatCode": "image_png", "isFullScreen": false}}