{"id":4331,"questionCode":"10060039","questionTemplateId":1,"noteDisplayTypeCode":"XNA","questionFrameDisplayTypeCode":"XNA","answerTextDisplayTypeCode":"ALWAYS","questionTextDisplayTypeCode":"XNA","questionText":"\u0022Motorov\u00E9 vozidlo\u0022:","explanationNote":null,"maxNoOfDisplays":-1,"maxPostDisplayTime":-1,"basketScopeId":9,"basketScopeOrder":0,"pointsCount":2,"validFrom":"2010-08-01T00:00:00","validTo":"2099-12-31T00:00:00","answersOrder":"0000","questionAnswers":[{"id":3424586,"answerText":"je nekolejov\u00E9 vozidlo poh\u00E1n\u011Bn\u00E9 vlastn\u00ED pohonnou jednotkou a trolejbus.","mediaContent":null,"sortOrderNumber":1,"isCorrect":true},{"id":3424587,"answerText":"je vozidlo poh\u00E1n\u011Bn\u00E9 vlastn\u00ED pohonnou jednotkou, ne v\u0161ak trolejbus.","mediaContent":null,"sortOrderNumber":2,"isCorrect":false},{"id":3424588,"answerText":"je vozidlo poh\u00E1n\u011Bn\u00E9 vlastn\u00ED pohonnou jednotkou a tramvaj.","mediaContent":null,"sortOrderNumber":3,"isCorrect":false}],"mediaContent":null}