{"id": 5603, "questionCode": "23060041", "questionTemplateId": 2, "noteDisplayTypeCode": "XNA", "questionFrameDisplayTypeCode": "XNA", "answerTextDisplayTypeCode": "ALWAYS", "questionTextDisplayTypeCode": "XNA", "questionText": "Při průjezdu zatáčkou na motocyklu:", "explanationNote": null, "maxNoOfDisplays": -1, "maxPostDisplayTime": -1, "basketScopeId": 10, "basketScopeOrder": 0, "pointsCount": 2, "validFrom": "2023-07-09T00:00:00", "validTo": "2100-01-01T00:00:00", "answersOrder": "0000", "questionAnswers": [{"id": 3429989, "answerText": "Pokud je zatáčka pravotočivá, pomáhá si řidič kontaktem pravého chodidla nohy se zemí.", "mediaContent": null, "sortOrderNumber": 1, "isCorrect": false}, {"id": 3429990, "answerText": "Zůstávají obě dvě nohy na stupačkách.", "mediaContent": null, "sortOrderNumber": 2, "isCorrect": true}, {"id": 3429991, "answerText": "Pokud je zatáčka pravotočivá, pomáhá si řidič kontaktem levého chodidla nohy se zemí.", "mediaContent": null, "sortOrderNumber": 3, "isCorrect": false}], "mediaContent": {"printMediaName": "Q_W_5603.png", "mediaUrl": "/binary_content_storage/Q_W_5603.png", "mediaDataHash": "9eb8cf4ba2e9d190e10bb2aa0606b82b2ac5674be5b0d66e9b67a0f8a9a29a1c", "mediaFormatCode": "image_png", "isFullScreen": false}}