{"id": 5660, "questionCode": "24070005", "questionTemplateId": 4, "noteDisplayTypeCode": "ALWAYS", "questionFrameDisplayTypeCode": "QTEXT", "answerTextDisplayTypeCode": "ALWAYS", "questionTextDisplayTypeCode": "ALWAYS", "questionText": "Dodrželi řidiči vozidel odbočující na křižovatce vlevo pravidla provozu?", "explanationNote": "Spusťte animaci tlačítkem „Přehrát“ (kliknutím na video). Pozorně sledujte situaci. Následně odpovězte na otázku.", "maxNoOfDisplays": -1, "maxPostDisplayTime": -1, "basketScopeId": 12, "basketScopeOrder": 0, "pointsCount": 4, "validFrom": "2024-07-28T00:00:00", "validTo": "2100-01-01T00:00:00", "answersOrder": "0000", "questionAnswers": [{"id": 3430159, "answerText": "Ne, měli se správně vyhýbat vlevo.", "mediaContent": null, "sortOrderNumber": 1, "isCorrect": true}, {"id": 3430160, "answerText": "Ano, oba dali znamení o změně směru jízdy.", "mediaContent": null, "sortOrderNumber": 2, "isCorrect": false}, {"id": 3430161, "answerText": "Ne, před odbočováním vlevo měli povinnost se zařadit co nejblíže k pravému okraji vozovky.", "mediaContent": null, "sortOrderNumber": 3, "isCorrect": false}], "mediaContent": {"printMediaName": "Q_W_5660.mp4", "mediaUrl": "/binary_content_storage/Q_W_5660.mp4", "mediaDataHash": "8ef93f48570baf09954040805f9612851e3fea252d3cd510dd7364173d126727", "mediaFormatCode": "video_mp4", "isFullScreen": true}}