{"id":2867,"questionCode":"06060133","questionTemplateId":1,"noteDisplayTypeCode":"XNA","questionFrameDisplayTypeCode":"XNA","answerTextDisplayTypeCode":"ALWAYS","questionTextDisplayTypeCode":"XNA","questionText":"P\u0159ednost p\u0159i \u010Derp\u00E1n\u00ED pohonn\u00FDch hmot maj\u00ED:","explanationNote":null,"maxNoOfDisplays":-1,"maxPostDisplayTime":-1,"basketScopeId":9,"basketScopeOrder":0,"pointsCount":2,"validFrom":"2006-06-11T00:00:00","validTo":"2099-12-31T00:00:00","answersOrder":"0000","questionAnswers":[{"id":28121,"answerText":"\u0158idi\u010Di vozidel s pr\u00E1vem p\u0159ednostn\u00ED j\u00EDzdy.","mediaContent":null,"sortOrderNumber":1,"isCorrect":true},{"id":28122,"answerText":"\u0158idi\u010Di vozidel hromadn\u00E9 dopravy osob (nap\u0159. autobus\u016F).","mediaContent":null,"sortOrderNumber":2,"isCorrect":false},{"id":28123,"answerText":"\u0158idi\u010Di vozidel p\u0159epravuj\u00EDc\u00EDch zbo\u017E\u00ED, kter\u00E9 podl\u00E9h\u00E1 rychl\u00E9 zk\u00E1ze.","mediaContent":null,"sortOrderNumber":3,"isCorrect":false}],"mediaContent":null}