{"id": 5460, "questionCode": "22050020", "questionTemplateId": 2, "noteDisplayTypeCode": "XNA", "questionFrameDisplayTypeCode": "XNA", "answerTextDisplayTypeCode": "ALWAYS", "questionTextDisplayTypeCode": "XNA", "questionText": "Řidič vozidla z výhledu hodlá pokračovat v jízdě vlevo. Přitom:", "explanationNote": null, "maxNoOfDisplays": -1, "maxPostDisplayTime": -1, "basketScopeId": 9, "basketScopeOrder": 0, "pointsCount": 2, "validFrom": "2022-06-05T00:00:00", "validTo": "2100-01-01T00:00:00", "answersOrder": "0000", "questionAnswers": [{"id": 3429562, "answerText": "nemusí dát přednost protijedoucímu vozidlu, neboť pokračuje po hlavní pozemní komunikaci.", "mediaContent": null, "sortOrderNumber": 1, "isCorrect": false}, {"id": 3429563, "answerText": "musí dát přednost protijedoucímu vozidlu.", "mediaContent": null, "sortOrderNumber": 2, "isCorrect": true}, {"id": 3429564, "answerText": "nemusí dát přednost protijedoucímu vozidlu, neboť jede na signál \"VOLNO\".", "mediaContent": null, "sortOrderNumber": 3, "isCorrect": false}], "mediaContent": {"printMediaName": "Q_W_5460.png", "mediaUrl": "/binary_content_storage/Q_W_5460.png", "mediaDataHash": "773d6ef62159951b1fbac969d3ec4a8f134daaf5be178c58d4db88c50fa769a1", "mediaFormatCode": "image_png", "isFullScreen": false}}