{"id":2083,"questionCode":"06060053","questionTemplateId":3,"noteDisplayTypeCode":"XNA","questionFrameDisplayTypeCode":"XNA","answerTextDisplayTypeCode":"ALWAYS","questionTextDisplayTypeCode":"XNA","questionText":"Kter\u00E1 z vyobrazen\u00FDch dopravn\u00EDch zna\u010Dek nepat\u0159\u00ED do zna\u010Dek upravuj\u00EDc\u00EDch p\u0159ednost?","explanationNote":null,"maxNoOfDisplays":-1,"maxPostDisplayTime":-1,"basketScopeId":11,"basketScopeOrder":0,"pointsCount":1,"validFrom":"2014-01-01T00:00:00","validTo":"2099-12-31T00:00:00","answersOrder":"0000","questionAnswers":[{"id":26121,"answerText":".","mediaContent":{"printMediaName":null,"mediaUrl":"/binary_content_storage/A_W_2083_26121.jpg","mediaDataHash":"a4273eeff30bf1bb86836722cb09d48d8062bb783d6d954ea287ee867e926c23","mediaFormatCode":"image_jpg","isFullScreen":false},"sortOrderNumber":1,"isCorrect":false},{"id":26122,"answerText":".","mediaContent":{"printMediaName":null,"mediaUrl":"/binary_content_storage/A_W_2083_26122.jpg","mediaDataHash":"7596815087f4bdf055188bfc1188bdb3e0ed30d627dfe5919d839fdf0569200a","mediaFormatCode":"image_jpg","isFullScreen":false},"sortOrderNumber":2,"isCorrect":false},{"id":26123,"answerText":".","mediaContent":{"printMediaName":null,"mediaUrl":"/binary_content_storage/A_W_2083_26123.jpg","mediaDataHash":"a6f5be2363ecb2e1dee30cee5e92d6cfec63035ce51594e37a491036271b7dc4","mediaFormatCode":"image_jpg","isFullScreen":false},"sortOrderNumber":3,"isCorrect":true}],"mediaContent":null}